femtorun/VERSION
femtorun/__init__.py
femtorun/dummy_runner.py
femtorun/io_spec.py
femtorun/io_spec_data.py
femtorun/runner.py
femtorun-3.1.1.dist-info/licenses/LICENSE
femtorun-3.1.1.dist-info/METADATA
femtorun-3.1.1.dist-info/WHEEL
femtorun-3.1.1.dist-info/top_level.txt
femtorun-3.1.1.dist-info/RECORD
