Metadata-Version: 2.4
Name: femtorun
Version: 3.1.1
Summary: Femtorun defines the runtime interface for Femtosense software
Home-page: https://femtosense.ai/
Author: Femtosense
Author-email: info@femtosense.ai
Project-URL: Source, https://github.com/femtosense/femtorun
Classifier: Development Status :: 3 - Alpha
Classifier: Intended Audience :: Developers
Classifier: Programming Language :: Python :: 3.6
Classifier: Programming Language :: Python :: 3.7
Classifier: Programming Language :: Python :: 3.8
Classifier: Programming Language :: Python :: 3 :: Only
Classifier: Operating System :: OS Independent
Requires-Python: >=3.6
License-File: LICENSE
Requires-Dist: numpy<3.0.0,>=1.18.0
Requires-Dist: pytest
Requires-Dist: networkx
Requires-Dist: pyyaml
Dynamic: author
Dynamic: author-email
Dynamic: classifier
Dynamic: description
Dynamic: description-content-type
Dynamic: home-page
Dynamic: license-file
Dynamic: project-url
Dynamic: requires-dist
Dynamic: requires-python
Dynamic: summary
